daisypy/vis/__init__.py
daisypy/vis/animate/__init__.py
daisypy/vis/animate/animate_depth_timeseries.py
daisypy/vis/animate/test/__init__.py
daisypy/vis/animate/test/conftest.py
daisypy/vis/animate/test/test_animate_depth_timeseries.py
daisypy/vis/io/__init__.py
daisypy/vis/io/dlf.py
daisypy/vis/io/test/__init__.py
daisypy/vis/io/test/test_dlf.py
daisypy/vis/plot/__init__.py
daisypy/vis/plot/bar.py
daisypy/vis/plot/base_plotter.py
daisypy/vis/plot/plot_annual.py
daisypy/vis/plot/plot_daily.py
daisypy/vis/plot/points_and_lines.py
daisypy/vis/plot/test/__init__.py
daisypy/vis/plot/test/conftest.py
daisypy/vis/plot/test/test_bar.py
daisypy/vis/plot/test/test_plot_annual.py
daisypy/vis/plot/test/test_plot_daily.py
daisypy/vis/plot/test/test_points_and_lines.py
daisypy/vis/test_helpers/__init__.py
daisypy/vis/test_helpers/compare_images.py
daisypy/vis/test_helpers/save_animation.py
daisypy/vis/test_helpers/test/__init__.py
daisypy/vis/test_helpers/test/test_compare_images.py
daisypy/vis/transform/__init__.py
daisypy/vis/transform/daisy_time_to_timestamp.py
daisypy/vis/transform/depth_wide_to_long.py
daisypy/vis/transform/test/__init__.py
daisypy/vis/transform/test/conftest.py
daisypy/vis/transform/test/test_daisy_time_to_timestamp.py
daisypy/vis/transform/test/test_depth_wide_to_long.py
daisypy_vis-0.3.1.dist-info/LICENSE
daisypy_vis-0.3.1.dist-info/METADATA
daisypy_vis-0.3.1.dist-info/WHEEL
daisypy_vis-0.3.1.dist-info/top_level.txt
daisypy_vis-0.3.1.dist-info/RECORD
