Metadata-Version: 2.1
Name: daisypy-vis
Version: 0.3.1
Summary: Visualization module for Daisy log files (dlf)
Author-email: Silas Nyboe Ørting <silas@di.ku.dk>
Project-URL: Homepage, https://daisy.ku.dk/
Project-URL: Repository, https://github.com/daisy-model/daisy-vis
Project-URL: Issues, https://github.com/daisy-model/daisy-vis/issues
Classifier: License :: OSI Approved :: GNU General Public License v3 or later (GPLv3+)
Classifier: Programming Language :: Python :: 3
Requires-Python: >=3.11
License-File: LICENSE
Requires-Dist: pandas
Requires-Dist: matplotlib
Requires-Dist: plotly
Requires-Dist: dash
Provides-Extra: all
Requires-Dist: coverage ; extra == 'all'
Requires-Dist: pytest ; extra == 'all'
Requires-Dist: pytest-mpl ; extra == 'all'
Requires-Dist: kaleido ; extra == 'all'
Requires-Dist: pillow ; extra == 'all'
Requires-Dist: pylint ; extra == 'all'
Provides-Extra: lint
Requires-Dist: pylint ; extra == 'lint'
Requires-Dist: pytest ; extra == 'lint'
Requires-Dist: pillow ; extra == 'lint'
Provides-Extra: test
Requires-Dist: coverage ; extra == 'test'
Requires-Dist: pytest ; extra == 'test'
Requires-Dist: pytest-mpl ; extra == 'test'
Requires-Dist: kaleido ; extra == 'test'
Requires-Dist: pillow ; extra == 'test'
